libearth/__init__.py
libearth/codecs.py
libearth/crawler.py
libearth/feed.py
libearth/repository.py
libearth/sanitizer.py
libearth/schema.py
libearth/session.py
libearth/stage.py
libearth/subscribe.py
libearth/tz.py
libearth/version.py
libearth/compat/__init__.py
libearth/compat/clrxmlreader.py
libearth/compat/etree.py
libearth/compat/parallel.py
libearth/compat/xmlpullreader.py
libearth/parser/__init__.py
libearth/parser/atom.py
libearth/parser/autodiscovery.py
libearth/parser/rss2.py
libearth/parser/util.py
libearth-0.3.1.dist-info/DESCRIPTION.rst
libearth-0.3.1.dist-info/entry_points.txt
libearth-0.3.1.dist-info/METADATA
libearth-0.3.1.dist-info/metadata.json
libearth-0.3.1.dist-info/RECORD
libearth-0.3.1.dist-info/top_level.txt
libearth-0.3.1.dist-info/WHEEL
